journal_digital/NameSeconds.py
journal_digital/__init__.py
journal_digital/blank_transcripts.py
journal_digital/corpus.py
journal_digital/measure.py
journal_digital/name_to_path.py
journal_digital/settings.py
journal_digital/transcribe.py
journal_digital-2025.10.13.dist-info/METADATA
journal_digital-2025.10.13.dist-info/WHEEL
journal_digital-2025.10.13.dist-info/licenses/LICENSE
journal_digital-2025.10.13.dist-info/RECORD
