Metadata-Version: 2.4
Name: journal_digital
Version: 2025.10.13
Summary: Transcriptions from the Swedish newsreel archive Journal Digital
Project-URL: Homepage, https://modernatider1936.se
Project-URL: Repository, https://github.com/Modern36/journal_digital_corpus
Author-email: Robert Aspenskog <robert.aspenskog@gmail.com>, Mathias Johansson <MathiasJoha@gmail.com>
Maintainer-email: Mathias Johansson <MathiasJoha@gmail.com>, Robert Aspenskog <robert.aspenskog@gmail.com>
License: CC-BY-NC-4.0
License-File: LICENSE
Keywords: automatic speech recognition,intertitle,newsreels,speech-to-text,swedish,transcription,whisperx
Classifier: Development Status :: 4 - Beta
Classifier: Environment :: GPU :: NVIDIA CUDA
Classifier: Framework :: Pytest
Classifier: Intended Audience :: Science/Research
Classifier: Operating System :: MacOS
Classifier: Operating System :: POSIX :: Linux
Classifier: Programming Language :: Python :: 3.10
Classifier: Topic :: Multimedia :: Sound/Audio :: Analysis
Classifier: Topic :: Multimedia :: Sound/Audio :: Speech
Classifier: Topic :: Multimedia :: Video
Classifier: Topic :: Scientific/Engineering :: Artificial Intelligence
Classifier: Topic :: Scientific/Engineering :: Image Processing
Classifier: Topic :: Utilities
Requires-Dist: dotenv==0.9.9
Requires-Dist: pandas==2.2.3
Requires-Dist: python-dotenv==1.0.1
Requires-Dist: tqdm==4.67.1
Provides-Extra: dev
Requires-Dist: pytest==8.3.5; extra == 'dev'
Requires-Dist: stum==0.2.0; extra == 'dev'
Requires-Dist: swescribe[whisperx]==0.1.0; extra == 'dev'
Requires-Dist: tqdm==4.67.1; extra == 'dev'
